docs/examples/simple_design/src/adder.sv
// This file is public domain, it can be freely copied without restrictions.
// SPDX-License-Identifier: CC0-1.0
// Adder DUT
`timescale 1ns/1ps

module adder #(
  parameter integer DATA_WIDTH = 4
) (
  input  logic unsigned [DATA_WIDTH-1:0] A,
  input  logic unsigned [DATA_WIDTH-1:0] B,
  output logic unsigned [DATA_WIDTH:0]   X
);

  assign X = A + B;

  // Dump waves
  initial begin
    $dumpfile("dump.vcd");
    $dumpvars(1, adder);
  end

endmodule

docs/examples/designs/simple_design/simple_design/tb/dump.vcd
$date
	Mon Jul  3 17:27:49 2023
$end
$version
	Icarus Verilog
$end
$timescale
	1ps
$end
$scope module adder $end
$var wire 4 ! A [3:0] $end
$var wire 4 " B [3:0] $end
$var wire 5 # X [4:0] $end
$var parameter 32 $ DATA_WIDTH $end
$upscope $end
$enddefinitions $end
$comment Show the parameter values. $end
$dumpall
b100 $
$end
#0
$dumpvars
b1111 #
b1010 "
b101 !
$end
#2001
b1001 "
b10010 #
b1001 !
#4001
b1011 "
b1011 #
b0 !
#6001
b101 "
b1001 #
b100 !
#8001
b0 "
b101 #
b101 !
#10001
b11 #
b11 !
#12001
b1011 "
b10000 #
b101 !
#14001
b101 "
b1101 #
b1000 !
#16001
b100 "
b10001 #
b1101 !
#18001
b11 "
b1100 #
b1001 !
#20001
b1111 "
b11010 #
b1011 !
